{"namespace":"HajimeDesignSystem_6d37a4","components":[],"startingPoints":[],"cards":[{"path":"distributor-app.html","group":"Brand","name":"Distributor App"},{"path":"distributor-portal.html","group":"Brand","name":"Distributor Portal"},{"path":"global-markets.html","group":"Brand","subtitle":"Three variations on canvas — classic KPIs, cartographic, ops-timeline","name":"Global markets dashboard"},{"path":"hajime-app.html","group":"Brand","viewport":"1440x1080","subtitle":"Full clickable prototype — all 5 roles, all modules, real routing + state mutations","name":"Hajime — Full App Prototype"},{"path":"hq-operator-app.html","group":"Brand","name":"HQ Operator App"},{"path":"manufacturer-app.html","group":"Brand","name":"Manufacturer App"},{"path":"preview/buttons.html","group":"Brand","viewport":"900x120","subtitle":"Primary sumi · outline · accent CTA","name":"Buttons"},{"path":"preview/colors-accent.html","group":"Brand","viewport":"780x140","subtitle":"Signature accent + gradient","name":"Barrel gold"},{"path":"preview/colors-neutrals.html","group":"Brand","viewport":"780x140","subtitle":"Warm stone palette (paper → sumi)","name":"Neutrals"},{"path":"preview/colors-semantic.html","group":"Brand","viewport":"780x160","subtitle":"Success · Warning · Destructive · Info","name":"Semantic tokens"},{"path":"preview/colors-sidebar.html","group":"Brand","viewport":"780x160","subtitle":"Deep sumi ink surface","name":"Sidebar palette"},{"path":"preview/form-fields.html","group":"Brand","viewport":"720x260","subtitle":"Input · Select · Textarea","name":"Form fields"},{"path":"preview/icons.html","group":"Brand","viewport":"900x180","subtitle":"Lucide · 1.75 stroke · 20px","name":"Iconography"},{"path":"preview/logo.html","group":"Brand","viewport":"700x200","subtitle":"Hajime wordmark · light & dark","name":"Logo"},{"path":"preview/radii.html","group":"Brand","viewport":"780x140","subtitle":"sm → full · default 10px","name":"Radii"},{"path":"preview/shadows.html","group":"Brand","viewport":"780x180","subtitle":"soft / lifted / float","name":"Elevation"},{"path":"preview/spacing.html","group":"Brand","viewport":"780x130","subtitle":"4 / 8 / 12 / 16 / 20 / 24 / 32 / 40 / 48","name":"Spacing scale"},{"path":"preview/stat-cards.html","group":"Brand","viewport":"900x180","subtitle":"KPI tiles · default / accent / warning","name":"Stat cards"},{"path":"preview/status-badges.html","group":"Brand","viewport":"900x100","subtitle":"Dot + pill for order / shipment lifecycle","name":"Status badges"},{"path":"preview/table.html","group":"Brand","viewport":"900x220","subtitle":"Row-hover · mono SKU · status pill","name":"Data table"},{"path":"preview/type-body.html","group":"Brand","viewport":"840x220","subtitle":"DM Sans · body / muted / button / eyebrow","name":"Body type"},{"path":"preview/type-display.html","group":"Brand","viewport":"840x180","subtitle":"Cormorant Garamond · self-hosted · H1–H3","name":"Display type"},{"path":"preview/type-mono.html","group":"Brand","viewport":"840x160","subtitle":"JetBrains Mono + Cormorant tabular numerals","name":"Mono & numerals"},{"path":"rep-mobile.html","group":"Brand","subtitle":"Full flow: login → day overview → account → stock check → draft → confirm → visit note","name":"Sales Rep Mobile Prototype"},{"path":"retail-store-app.html","group":"Brand","name":"Retail Store App"},{"path":"retail-store-portal.html","group":"Brand","name":"Retail Store Portal"},{"path":"role-journeys.html","group":"Brand","viewport":"1920x1080","subtitle":"14 slides — five roles, end-to-end journeys","name":"role-journeys"},{"path":"sales-rep-app.html","group":"Brand","name":"Sales Rep App"},{"path":"sales-rep-portal.html","group":"Brand","name":"Sales Rep Portal"},{"path":"ui-kit-auth.html","group":"Brand","viewport":"1400x900","subtitle":"Role picker + credentials panel on sumi ink","name":"UI Kit — Auth / Role picker"},{"path":"ui-kit-operator-dashboard.html","group":"Brand","viewport":"1440x1200","subtitle":"Brand operator — Command center showcasing nav, KPIs, chart, alerts, table","name":"UI Kit — Brand Operator Dashboard"},{"path":"ui-kit-retail-store.html","group":"Brand","viewport":"1360x1200","subtitle":"Retail home: live tracker + reorder picks","name":"UI Kit — Retail Store"}],"templates":[],"globalCssPaths":["colors_and_type.css"],"tokens":[{"name":"--background","value":"40 18% 97%","kind":"color","definedIn":"colors_and_type.css","annotation":"color"},{"name":"--foreground","value":"24 10% 10%","kind":"color","definedIn":"colors_and_type.css","annotation":"color"},{"name":"--card","value":"40 20% 99%","kind":"color","definedIn":"colors_and_type.css","annotation":"color"},{"name":"--card-foreground","value":"24 10% 10%","kind":"color","definedIn":"colors_and_type.css","annotation":"color"},{"name":"--popover","value":"40 20% 99%","kind":"color","definedIn":"colors_and_type.css","annotation":"color"},{"name":"--popover-foreground","value":"24 10% 10%","kind":"color","definedIn":"colors_and_type.css","annotation":"color"},{"name":"--secondary","value":"35 16% 93%","kind":"color","definedIn":"colors_and_type.css","annotation":"color"},{"name":"--secondary-foreground","value":"24 10% 10%","kind":"color","definedIn":"colors_and_type.css","annotation":"color"},{"name":"--muted","value":"37 14% 94%","kind":"color","definedIn":"colors_and_type.css","annotation":"color"},{"name":"--muted-foreground","value":"24 6% 50%","kind":"color","definedIn":"colors_and_type.css","annotation":"color"},{"name":"--border","value":"35 12% 89%","kind":"color","definedIn":"colors_and_type.css","annotation":"color"},{"name":"--input","value":"35 12% 89%","kind":"color","definedIn":"colors_and_type.css","annotation":"color"},{"name":"--ring","value":"40 88% 42%","kind":"color","definedIn":"colors_and_type.css","annotation":"color"},{"name":"--primary","value":"24 10% 10%","kind":"color","definedIn":"colors_and_type.css","annotation":"color"},{"name":"--primary-foreground","value":"40 20% 97%","kind":"color","definedIn":"colors_and_type.css","annotation":"color"},{"name":"--accent","value":"40 88% 42%","kind":"color","definedIn":"colors_and_type.css","annotation":"color"},{"name":"--accent-foreground","value":"40 20% 97%","kind":"color","definedIn":"colors_and_type.css","annotation":"color"},{"name":"--accent-hover","value":"32 78% 48%","kind":"color","definedIn":"colors_and_type.css","annotation":"color"},{"name":"--success","value":"158 56% 36%","kind":"color","definedIn":"colors_and_type.css","annotation":"color"},{"name":"--success-foreground","value":"0 0% 100%","kind":"color","definedIn":"colors_and_type.css","annotation":"color"},{"name":"--warning","value":"38 90% 50%","kind":"color","definedIn":"colors_and_type.css","annotation":"color"},{"name":"--warning-foreground","value":"24 10% 10%","kind":"color","definedIn":"colors_and_type.css","annotation":"color"},{"name":"--destructive","value":"0 68% 48%","kind":"color","definedIn":"colors_and_type.css","annotation":"color"},{"name":"--destructive-foreground","value":"0 0% 100%","kind":"color","definedIn":"colors_and_type.css","annotation":"color"},{"name":"--info","value":"215 72% 50%","kind":"color","definedIn":"colors_and_type.css","annotation":"color"},{"name":"--info-foreground","value":"0 0% 100%","kind":"color","definedIn":"colors_and_type.css","annotation":"color"},{"name":"--sidebar-background","value":"24 12% 8%","kind":"color","definedIn":"colors_and_type.css","annotation":"color"},{"name":"--sidebar-foreground","value":"35 12% 78%","kind":"color","definedIn":"colors_and_type.css","annotation":"color"},{"name":"--sidebar-primary","value":"40 88% 42%","kind":"color","definedIn":"colors_and_type.css","annotation":"color"},{"name":"--sidebar-primary-foreground","value":"24 12% 8%","kind":"color","definedIn":"colors_and_type.css","annotation":"color"},{"name":"--sidebar-accent","value":"24 10% 13%","kind":"color","definedIn":"colors_and_type.css","annotation":"color"},{"name":"--sidebar-accent-foreground","value":"35 14% 90%","kind":"color","definedIn":"colors_and_type.css","annotation":"color"},{"name":"--sidebar-border","value":"24 10% 15%","kind":"color","definedIn":"colors_and_type.css","annotation":"color"},{"name":"--sidebar-ring","value":"40 88% 42%","kind":"color","definedIn":"colors_and_type.css","annotation":"color"},{"name":"--surface-elevated","value":"40 20% 100%","kind":"color","definedIn":"colors_and_type.css","annotation":"color"},{"name":"--surface-sunken","value":"37 14% 94%","kind":"color","definedIn":"colors_and_type.css","annotation":"color"},{"name":"--glass-bg","value":"40 20% 99% / 0.8","kind":"color","definedIn":"colors_and_type.css","annotation":"color"},{"name":"--glass-border","value":"35 12% 89% / 0.6","kind":"color","definedIn":"colors_and_type.css","annotation":"color"},{"name":"--radius","value":"0.625rem","kind":"radius","definedIn":"colors_and_type.css"},{"name":"--radius-sm","value":"calc(var(--radius) - 4px)","kind":"radius","definedIn":"colors_and_type.css"},{"name":"--radius-md","value":"calc(var(--radius) - 2px)","kind":"radius","definedIn":"colors_and_type.css"},{"name":"--radius-lg","value":"var(--radius)","kind":"radius","definedIn":"colors_and_type.css"},{"name":"--radius-xl","value":"calc(var(--radius) + 4px)","kind":"radius","definedIn":"colors_and_type.css"},{"name":"--radius-2xl","value":"calc(var(--radius) + 8px)","kind":"radius","definedIn":"colors_and_type.css"},{"name":"--radius-full","value":"9999px","kind":"radius","definedIn":"colors_and_type.css"},{"name":"--shadow-soft","value":"0 1px 2px hsl(24 10% 10% / 0.04), 0 4px 12px hsl(24 10% 10% / 0.03)","kind":"shadow","definedIn":"colors_and_type.css"},{"name":"--shadow-lifted","value":"0 2px 4px hsl(24 10% 10% / 0.06), 0 8px 24px hsl(24 10% 10% / 0.06)","kind":"shadow","definedIn":"colors_and_type.css"},{"name":"--shadow-float","value":"0 4px 8px hsl(24 10% 10% / 0.06), 0 16px 40px hsl(24 10% 10% / 0.1)","kind":"shadow","definedIn":"colors_and_type.css"},{"name":"--ease-out-expo","value":"cubic-bezier(0.16, 1, 0.3, 1)","kind":"other","definedIn":"colors_and_type.css","annotation":"other"},{"name":"--ease-in-out","value":"cubic-bezier(0.65, 0, 0.35, 1)","kind":"other","definedIn":"colors_and_type.css","annotation":"other"},{"name":"--space-1","value":"0.25rem","kind":"spacing","definedIn":"colors_and_type.css"},{"name":"--space-2","value":"0.5rem","kind":"spacing","definedIn":"colors_and_type.css"},{"name":"--space-3","value":"0.75rem","kind":"spacing","definedIn":"colors_and_type.css"},{"name":"--space-4","value":"1rem","kind":"spacing","definedIn":"colors_and_type.css"},{"name":"--space-5","value":"1.25rem","kind":"spacing","definedIn":"colors_and_type.css"},{"name":"--space-6","value":"1.5rem","kind":"spacing","definedIn":"colors_and_type.css"},{"name":"--space-8","value":"2rem","kind":"spacing","definedIn":"colors_and_type.css"},{"name":"--space-10","value":"2.5rem","kind":"spacing","definedIn":"colors_and_type.css"},{"name":"--space-12","value":"3rem","kind":"spacing","definedIn":"colors_and_type.css"},{"name":"--font-display","value":"'Cormorant Garamond', Georgia, serif","kind":"font","definedIn":"colors_and_type.css"},{"name":"--font-body","value":"'DM Sans', system-ui, -apple-system, sans-serif","kind":"font","definedIn":"colors_and_type.css"},{"name":"--font-mono","value":"'JetBrains Mono', Menlo, monospace","kind":"font","definedIn":"colors_and_type.css"},{"name":"--fs-2xs","value":"0.625rem","kind":"spacing","definedIn":"colors_and_type.css"},{"name":"--fs-xs","value":"0.75rem","kind":"spacing","definedIn":"colors_and_type.css"},{"name":"--fs-sm","value":"0.875rem","kind":"spacing","definedIn":"colors_and_type.css"},{"name":"--fs-base","value":"1rem","kind":"spacing","definedIn":"colors_and_type.css"},{"name":"--fs-lg","value":"1.125rem","kind":"spacing","definedIn":"colors_and_type.css"},{"name":"--fs-xl","value":"1.25rem","kind":"spacing","definedIn":"colors_and_type.css"},{"name":"--fs-2xl","value":"1.5rem","kind":"spacing","definedIn":"colors_and_type.css"},{"name":"--fs-3xl","value":"1.875rem","kind":"spacing","definedIn":"colors_and_type.css"},{"name":"--fs-4xl","value":"2.25rem","kind":"spacing","definedIn":"colors_and_type.css"},{"name":"--fs-5xl","value":"3rem","kind":"spacing","definedIn":"colors_and_type.css"}],"themes":[],"fonts":[{"family":"Cormorant Garamond","weight":"300","style":"normal","cssPath":"colors_and_type.css","files":["fonts/CormorantGaramond-Light.ttf"]},{"family":"Cormorant Garamond","weight":"300","style":"italic","cssPath":"colors_and_type.css","files":["fonts/CormorantGaramond-LightItalic.ttf"]},{"family":"Cormorant Garamond","weight":"400","style":"normal","cssPath":"colors_and_type.css","files":["fonts/CormorantGaramond-Regular.ttf"]},{"family":"Cormorant Garamond","weight":"400","style":"italic","cssPath":"colors_and_type.css","files":["fonts/CormorantGaramond-Italic.ttf"]},{"family":"Cormorant Garamond","weight":"500","style":"normal","cssPath":"colors_and_type.css","files":["fonts/CormorantGaramond-Medium.ttf"]},{"family":"Cormorant Garamond","weight":"500","style":"italic","cssPath":"colors_and_type.css","files":["fonts/CormorantGaramond-MediumItalic.ttf"]},{"family":"Cormorant Garamond","weight":"600","style":"normal","cssPath":"colors_and_type.css","files":["fonts/CormorantGaramond-SemiBold.ttf"]},{"family":"Cormorant Garamond","weight":"600","style":"italic","cssPath":"colors_and_type.css","files":["fonts/CormorantGaramond-SemiBoldItalic.ttf"]},{"family":"Cormorant Garamond","weight":"700","style":"normal","cssPath":"colors_and_type.css","files":["fonts/CormorantGaramond-Bold.ttf"]},{"family":"Cormorant Garamond","weight":"700","style":"italic","cssPath":"colors_and_type.css","files":["fonts/CormorantGaramond-BoldItalic.ttf"]}],"brandFonts":[{"family":"Cormorant Garamond","status":"ok","tokens":["--font-display"],"path":"colors_and_type.css"},{"family":"DM Sans","status":"ok","tokens":["--font-body"],"path":"colors_and_type.css"},{"family":"JetBrains Mono","status":"ok","tokens":["--font-mono"],"path":"colors_and_type.css"}],"source":"spa"}